nearness/__init__.py
nearness/_annoy.py
nearness/_autofaiss.py
nearness/_base/__init__.py
nearness/_base/_config.py
nearness/_base/_experimental.py
nearness/_base/_helpers.py
nearness/_base/_neighbors.py
nearness/_faiss.py
nearness/_hnsw.py
nearness/_jax.py
nearness/_numpy.py
nearness/_scann.py
nearness/_scipy.py
nearness/_sklearn.py
nearness/_torch.py
nearness/_usearch.py
nearness/py.typed
nearness-0.2.4.dist-info/LICENSE.txt
nearness-0.2.4.dist-info/METADATA
nearness-0.2.4.dist-info/WHEEL
nearness-0.2.4.dist-info/RECORD
